{
    "author_handle": "corey@joinhandshake.com",
    "author_name": "Corey Carter",
    "created_at": "2022-02-11T04:04:56.300670+00:00",
    "description": "",
    "id": "2he-zmk-uzb",
    "is_read_only": false,
    "layout_type": "ordered",
    "modified_at": "2022-02-15T03:37:03.402153+00:00",
    "notify_list": [],
    "reflow_type": "fixed",
    "restricted_roles": [],
    "template_variables": [],
    "title": "Employer Lifecycle Iterable",
    "url": "/dashboard/2he-zmk-uzb/employer-lifecycle-iterable",
    "widgets": [
        {
            "definition": {
                "layout_type": "ordered",
                "title": "Iterable",
                "type": "group",
                "widgets": [
                    {
                        "definition": {
                            "color_preference": "text",
                            "count": 50,
                            "display_format": "list",
                            "hide_zero_counts": true,
                            "query": "tag:(Iterable)",
                            "show_last_triggered": false,
                            "show_priority": false,
                            "sort": "status,asc",
                            "start": 0,
                            "summary_type": "monitors",
                            "title": "Iterable Queue Monitor",
                            "title_align": "left",
                            "title_size": "13",
                            "type": "manage_status"
                        },
                        "id": 2004807486896992,
                        "layout": {
                            "height": 2,
                            "width": 4,
                            "x": 0,
                            "y": 0
                        }
                    },
                    {
                        "definition": {
                            "legend_columns": [
                                "avg",
                                "min",
                                "max",
                                "value",
                                "sum"
                            ],
                            "legend_layout": "vertical",
                            "markers": [],
                            "requests": [
                                {
                                    "display_type": "line",
                                    "formulas": [
                                        {
                                            "formula": "query1"
                                        },
                                        {
                                            "formula": "query2"
                                        },
                                        {
                                            "formula": "query3"
                                        }
                                    ],
                                    "on_right_yaxis": false,
                                    "queries": [
                                        {
                                            "data_source": "metrics",
                                            "name": "query1",
                                            "query": "avg:handshake.iterable.unprocessed_events_on_queue{app:handshake}"
                                        },
                                        {
                                            "data_source": "metrics",
                                            "name": "query2",
                                            "query": "avg:handshake.iterable.unprocessed_email_updates_on_queue{app:handshake}"
                                        },
                                        {
                                            "data_source": "metrics",
                                            "name": "query3",
                                            "query": "avg:handshake.iterable.unprocessed_users_on_queue{app:handshake}"
                                        }
                                    ],
                                    "response_format": "timeseries",
                                    "style": {
                                        "line_type": "solid",
                                        "line_width": "normal",
                                        "palette": "dog_classic"
                                    }
                                }
                            ],
                            "show_legend": false,
                            "title": "Average Unprocessed Records left on Queue",
                            "title_align": "left",
                            "title_size": "16",
                            "type": "timeseries",
                            "yaxis": {
                                "include_zero": true,
                                "label": "",
                                "max": "auto",
                                "min": "auto",
                                "scale": "linear"
                            }
                        },
                        "id": 8185550100356854,
                        "layout": {
                            "height": 2,
                            "width": 4,
                            "x": 4,
                            "y": 0
                        }
                    },
                    {
                        "definition": {
                            "legend_columns": [
                                "avg",
                                "min",
                                "max",
                                "value",
                                "sum"
                            ],
                            "legend_layout": "vertical",
                            "markers": [],
                            "requests": [
                                {
                                    "display_type": "line",
                                    "formulas": [
                                        {
                                            "formula": "query1"
                                        },
                                        {
                                            "formula": "query2"
                                        },
                                        {
                                            "formula": "query3"
                                        },
                                        {
                                            "formula": "query4"
                                        },
                                        {
                                            "formula": "query5"
                                        },
                                        {
                                            "formula": "query6"
                                        },
                                        {
                                            "formula": "query7"
                                        },
                                        {
                                            "formula": "query8"
                                        }
                                    ],
                                    "on_right_yaxis": false,
                                    "queries": [
                                        {
                                            "data_source": "metrics",
                                            "name": "query1",
                                            "query": "sum:handshake.iterable_queue.queued.events.students.activation{app:handshake,env:production}"
                                        },
                                        {
                                            "data_source": "metrics",
                                            "name": "query2",
                                            "query": "sum:handshake.iterable_queue.queued.events.students.application{app:handshake,env:production}"
                                        },
                                        {
                                            "data_source": "metrics",
                                            "name": "query3",
                                            "query": "sum:handshake.iterable_queue.queued.events.students.jobReview{app:handshake,env:production}"
                                        },
                                        {
                                            "data_source": "metrics",
                                            "name": "query4",
                                            "query": "sum:handshake.iterable_queue.queued.events.students.loggedIn{app:handshake,env:production}"
                                        },
                                        {
                                            "data_source": "metrics",
                                            "name": "query5",
                                            "query": "sum:handshake.iterable_queue.queued.events.students.registration{app:handshake,env:production}"
                                        },
                                        {
                                            "data_source": "metrics",
                                            "name": "query6",
                                            "query": "sum:handshake.iterable_queue.queued.events.employers.employerJob{app:handshake,env:production}"
                                        },
                                        {
                                            "data_source": "metrics",
                                            "name": "query7",
                                            "query": "sum:handshake.iterable_queue.queued.events.employers.jobPosting{app:handshake,env:production}"
                                        },
                                        {
                                            "data_source": "metrics",
                                            "name": "query8",
                                            "query": "sum:handshake.iterable_queue.queued.events.employers.employerRegistration{app:handshake,env:production}"
                                        }
                                    ],
                                    "response_format": "timeseries",
                                    "style": {
                                        "line_type": "solid",
                                        "line_width": "normal",
                                        "palette": "dog_classic"
                                    }
                                }
                            ],
                            "show_legend": false,
                            "title": "Event types added to queue",
                            "title_align": "left",
                            "title_size": "16",
                            "type": "timeseries",
                            "yaxis": {
                                "include_zero": true,
                                "label": "",
                                "max": "auto",
                                "min": "auto",
                                "scale": "linear"
                            }
                        },
                        "id": 7317583949288826,
                        "layout": {
                            "height": 2,
                            "width": 4,
                            "x": 8,
                            "y": 0
                        }
                    },
                    {
                        "definition": {
                            "legend_columns": [
                                "avg",
                                "min",
                                "max",
                                "value",
                                "sum"
                            ],
                            "legend_layout": "vertical",
                            "markers": [],
                            "requests": [
                                {
                                    "display_type": "line",
                                    "formulas": [
                                        {
                                            "formula": "query1"
                                        }
                                    ],
                                    "on_right_yaxis": false,
                                    "queries": [
                                        {
                                            "data_source": "metrics",
                                            "name": "query1",
                                            "query": "avg:handshake.iterable.email_update_queue_size{app:handshake}"
                                        }
                                    ],
                                    "response_format": "timeseries",
                                    "style": {
                                        "line_type": "solid",
                                        "line_width": "normal",
                                        "palette": "dog_classic"
                                    }
                                }
                            ],
                            "show_legend": false,
                            "title": "Average Iterable User Email Queue Size",
                            "title_align": "left",
                            "title_size": "16",
                            "type": "timeseries",
                            "yaxis": {
                                "include_zero": true,
                                "label": "",
                                "max": "auto",
                                "min": "auto",
                                "scale": "linear"
                            }
                        },
                        "id": 8751226585453002,
                        "layout": {
                            "height": 2,
                            "width": 4,
                            "x": 0,
                            "y": 2
                        }
                    },
                    {
                        "definition": {
                            "legend_columns": [
                                "avg",
                                "min",
                                "max",
                                "value",
                                "sum"
                            ],
                            "legend_layout": "auto",
                            "markers": [],
                            "requests": [
                                {
                                    "display_type": "bars",
                                    "q": "max:handshake.iterable_queue.queued{env:production}.as_count()",
                                    "style": {
                                        "line_type": "solid",
                                        "line_width": "normal",
                                        "palette": "dog_classic"
                                    }
                                }
                            ],
                            "show_legend": false,
                            "title": "Max of Iterable Event Queue",
                            "title_align": "left",
                            "title_size": "16",
                            "type": "timeseries",
                            "yaxis": {
                                "include_zero": true,
                                "label": "",
                                "max": "auto",
                                "min": "auto",
                                "scale": "linear"
                            }
                        },
                        "id": 3757046656858408,
                        "layout": {
                            "height": 2,
                            "width": 4,
                            "x": 4,
                            "y": 2
                        }
                    },
                    {
                        "definition": {
                            "legend_columns": [
                                "avg",
                                "min",
                                "max",
                                "value",
                                "sum"
                            ],
                            "legend_layout": "auto",
                            "markers": [],
                            "requests": [
                                {
                                    "display_type": "bars",
                                    "q": "max:handshake.iterable_queue.synced_users{env:production}.as_count()",
                                    "style": {
                                        "line_type": "solid",
                                        "line_width": "normal",
                                        "palette": "dog_classic"
                                    }
                                }
                            ],
                            "show_legend": false,
                            "title": "Iterable Queue Synced (Student) Users",
                            "title_align": "left",
                            "title_size": "16",
                            "type": "timeseries",
                            "yaxis": {
                                "include_zero": true,
                                "label": "",
                                "max": "auto",
                                "min": "auto",
                                "scale": "linear"
                            }
                        },
                        "id": 3318352718625390,
                        "layout": {
                            "height": 2,
                            "width": 4,
                            "x": 8,
                            "y": 2
                        }
                    },
                    {
                        "definition": {
                            "legend_columns": [
                                "avg",
                                "min",
                                "max",
                                "value",
                                "sum"
                            ],
                            "legend_layout": "auto",
                            "markers": [],
                            "requests": [
                                {
                                    "display_type": "bars",
                                    "q": "sum:handshake.iterable_queue.synced_employer_users{env:production}.as_count()",
                                    "style": {
                                        "line_type": "solid",
                                        "line_width": "normal",
                                        "palette": "dog_classic"
                                    }
                                }
                            ],
                            "show_legend": false,
                            "title": "Iterable Queue Synced Employer Users",
                            "title_align": "left",
                            "title_size": "16",
                            "type": "timeseries",
                            "yaxis": {
                                "include_zero": true,
                                "label": "",
                                "max": "auto",
                                "min": "auto",
                                "scale": "linear"
                            }
                        },
                        "id": 255929802523974,
                        "layout": {
                            "height": 2,
                            "width": 4,
                            "x": 0,
                            "y": 4
                        }
                    },
                    {
                        "definition": {
                            "legend_columns": [
                                "avg",
                                "min",
                                "max",
                                "value",
                                "sum"
                            ],
                            "legend_layout": "auto",
                            "markers": [],
                            "requests": [
                                {
                                    "display_type": "bars",
                                    "formulas": [
                                        {
                                            "formula": "query1"
                                        }
                                    ],
                                    "queries": [
                                        {
                                            "data_source": "metrics",
                                            "name": "query1",
                                            "query": "avg:handshake.iterable_queue.queued{env:production}.as_count()"
                                        }
                                    ],
                                    "response_format": "timeseries",
                                    "style": {
                                        "line_type": "solid",
                                        "line_width": "normal",
                                        "palette": "dog_classic"
                                    }
                                }
                            ],
                            "show_legend": false,
                            "title": "Avg of Iterable Event Queue",
                            "title_align": "left",
                            "title_size": "16",
                            "type": "timeseries",
                            "yaxis": {
                                "include_zero": true,
                                "label": "",
                                "max": "auto",
                                "min": "auto",
                                "scale": "linear"
                            }
                        },
                        "id": 1798368749861224,
                        "layout": {
                            "height": 2,
                            "width": 4,
                            "x": 4,
                            "y": 4
                        }
                    },
                    {
                        "definition": {
                            "legend_columns": [
                                "avg",
                                "min",
                                "max",
                                "value",
                                "sum"
                            ],
                            "legend_layout": "vertical",
                            "markers": [],
                            "requests": [
                                {
                                    "display_type": "bars",
                                    "q": "avg:handshake.iterable_queue.sync_users_to_iterable.count{env:production}.as_rate()",
                                    "style": {
                                        "line_type": "solid",
                                        "line_width": "normal",
                                        "palette": "dog_classic"
                                    }
                                }
                            ],
                            "show_legend": false,
                            "title": "Iterable Queue Sync Users to Iterable Timing",
                            "title_align": "left",
                            "title_size": "16",
                            "type": "timeseries",
                            "yaxis": {
                                "include_zero": true,
                                "label": "",
                                "max": "auto",
                                "min": "auto",
                                "scale": "linear"
                            }
                        },
                        "id": 7204883843720152,
                        "layout": {
                            "height": 2,
                            "width": 4,
                            "x": 8,
                            "y": 4
                        }
                    },
                    {
                        "definition": {
                            "legend_columns": [
                                "avg",
                                "min",
                                "max",
                                "value",
                                "sum"
                            ],
                            "legend_layout": "vertical",
                            "markers": [],
                            "requests": [
                                {
                                    "display_type": "line",
                                    "formulas": [
                                        {
                                            "formula": "query1"
                                        }
                                    ],
                                    "on_right_yaxis": false,
                                    "queries": [
                                        {
                                            "data_source": "metrics",
                                            "name": "query1",
                                            "query": "avg:handshake.iterable.event_queue_batch_timing.max{env:production}"
                                        }
                                    ],
                                    "response_format": "timeseries",
                                    "style": {
                                        "line_type": "solid",
                                        "line_width": "normal",
                                        "palette": "dog_classic"
                                    }
                                }
                            ],
                            "show_legend": false,
                            "time": {},
                            "title": "Iterable Event Queue Timing",
                            "title_align": "left",
                            "title_size": "16",
                            "type": "timeseries",
                            "yaxis": {
                                "include_zero": true,
                                "label": "",
                                "max": "auto",
                                "min": "auto",
                                "scale": "linear"
                            }
                        },
                        "id": 2931685270357608,
                        "layout": {
                            "height": 2,
                            "width": 4,
                            "x": 0,
                            "y": 6
                        }
                    },
                    {
                        "definition": {
                            "legend_columns": [
                                "avg",
                                "min",
                                "max",
                                "value",
                                "sum"
                            ],
                            "legend_layout": "vertical",
                            "markers": [],
                            "requests": [
                                {
                                    "display_type": "line",
                                    "formulas": [
                                        {
                                            "formula": "query1"
                                        }
                                    ],
                                    "on_right_yaxis": false,
                                    "queries": [
                                        {
                                            "data_source": "metrics",
                                            "name": "query1",
                                            "query": "avg:handshake.iterable.email_queue_batch_timing.max{env:production}"
                                        }
                                    ],
                                    "response_format": "timeseries",
                                    "style": {
                                        "line_type": "solid",
                                        "line_width": "normal",
                                        "palette": "dog_classic"
                                    }
                                }
                            ],
                            "show_legend": false,
                            "time": {},
                            "title": "Iterable Email Queue Timing",
                            "title_align": "left",
                            "title_size": "16",
                            "type": "timeseries",
                            "yaxis": {
                                "include_zero": true,
                                "label": "",
                                "max": "auto",
                                "min": "auto",
                                "scale": "linear"
                            }
                        },
                        "id": 4552580637926482,
                        "layout": {
                            "height": 2,
                            "width": 4,
                            "x": 4,
                            "y": 6
                        }
                    },
                    {
                        "definition": {
                            "legend_columns": [
                                "avg",
                                "min",
                                "max",
                                "value",
                                "sum"
                            ],
                            "legend_layout": "vertical",
                            "markers": [],
                            "requests": [
                                {
                                    "display_type": "line",
                                    "formulas": [
                                        {
                                            "formula": "query1"
                                        }
                                    ],
                                    "on_right_yaxis": false,
                                    "queries": [
                                        {
                                            "data_source": "metrics",
                                            "name": "query1",
                                            "query": "avg:handshake.iterable.user_queue_batch_timing.max{env:production}"
                                        }
                                    ],
                                    "response_format": "timeseries",
                                    "style": {
                                        "line_type": "solid",
                                        "line_width": "normal",
                                        "palette": "dog_classic"
                                    }
                                }
                            ],
                            "show_legend": false,
                            "time": {},
                            "title": "Iterable User Queue Timing",
                            "title_align": "left",
                            "title_size": "16",
                            "type": "timeseries",
                            "yaxis": {
                                "include_zero": true,
                                "label": "",
                                "max": "auto",
                                "min": "auto",
                                "scale": "linear"
                            }
                        },
                        "id": 2890689621234902,
                        "layout": {
                            "height": 2,
                            "width": 4,
                            "x": 8,
                            "y": 6
                        }
                    },
                    {
                        "definition": {
                            "legend_columns": [
                                "avg",
                                "min",
                                "max",
                                "value",
                                "sum"
                            ],
                            "legend_layout": "vertical",
                            "markers": [],
                            "requests": [
                                {
                                    "display_type": "bars",
                                    "queries": [
                                        {
                                            "data_source": "metrics",
                                            "name": "query1",
                                            "query": "avg:handshake.iterable_queue.sync_events_to_iterable.count{env:production}.as_rate()"
                                        }
                                    ],
                                    "response_format": "timeseries",
                                    "style": {
                                        "line_type": "solid",
                                        "line_width": "normal",
                                        "palette": "dog_classic"
                                    }
                                }
                            ],
                            "show_legend": false,
                            "title": "Iterable Queue Sync Events to Iterable Timing",
                            "title_align": "left",
                            "title_size": "16",
                            "type": "timeseries",
                            "yaxis": {
                                "include_zero": true,
                                "label": "",
                                "max": "auto",
                                "min": "auto",
                                "scale": "linear"
                            }
                        },
                        "id": 8315393030929468,
                        "layout": {
                            "height": 2,
                            "width": 4,
                            "x": 0,
                            "y": 8
                        }
                    },
                    {
                        "definition": {
                            "legend_columns": [
                                "avg",
                                "min",
                                "max",
                                "value",
                                "sum"
                            ],
                            "legend_layout": "vertical",
                            "markers": [],
                            "requests": [
                                {
                                    "display_type": "bars",
                                    "queries": [
                                        {
                                            "data_source": "metrics",
                                            "name": "query1",
                                            "query": "sum:handshake.iterable_queue.synced{env:production}.as_count()"
                                        }
                                    ],
                                    "response_format": "timeseries",
                                    "style": {
                                        "line_type": "solid",
                                        "line_width": "normal",
                                        "palette": "dog_classic"
                                    }
                                }
                            ],
                            "show_legend": false,
                            "title": "Iterable Queue Sync (Student) Events",
                            "title_align": "left",
                            "title_size": "16",
                            "type": "timeseries",
                            "yaxis": {
                                "include_zero": true,
                                "label": "",
                                "max": "auto",
                                "min": "auto",
                                "scale": "linear"
                            }
                        },
                        "id": 2042217776377052,
                        "layout": {
                            "height": 2,
                            "width": 4,
                            "x": 4,
                            "y": 8
                        }
                    },
                    {
                        "definition": {
                            "legend_columns": [
                                "avg",
                                "min",
                                "max",
                                "value",
                                "sum"
                            ],
                            "legend_layout": "vertical",
                            "markers": [],
                            "requests": [
                                {
                                    "display_type": "bars",
                                    "queries": [
                                        {
                                            "data_source": "metrics",
                                            "name": "query1",
                                            "query": "sum:handshake.iterable.event_count{env:production}.as_count()"
                                        }
                                    ],
                                    "response_format": "timeseries",
                                    "style": {
                                        "line_type": "solid",
                                        "line_width": "normal",
                                        "palette": "dog_classic"
                                    }
                                }
                            ],
                            "show_legend": false,
                            "title": "Iterable Api Sync (Student) Events",
                            "title_align": "left",
                            "title_size": "16",
                            "type": "timeseries",
                            "yaxis": {
                                "include_zero": true,
                                "label": "",
                                "max": "auto",
                                "min": "auto",
                                "scale": "linear"
                            }
                        },
                        "id": 5315104980819252,
                        "layout": {
                            "height": 2,
                            "width": 4,
                            "x": 8,
                            "y": 8
                        }
                    },
                    {
                        "definition": {
                            "legend_columns": [
                                "avg",
                                "min",
                                "max",
                                "value",
                                "sum"
                            ],
                            "legend_layout": "vertical",
                            "markers": [],
                            "requests": [
                                {
                                    "display_type": "bars",
                                    "formulas": [
                                        {
                                            "formula": "query1"
                                        }
                                    ],
                                    "on_right_yaxis": false,
                                    "queries": [
                                        {
                                            "data_source": "metrics",
                                            "name": "query1",
                                            "query": "sum:handshake.iterable_queue.synced_employer_events{env:production}.as_count()"
                                        }
                                    ],
                                    "response_format": "timeseries",
                                    "style": {
                                        "line_type": "solid",
                                        "line_width": "normal",
                                        "palette": "dog_classic"
                                    }
                                }
                            ],
                            "show_legend": false,
                            "title": "Iterable Api Sync (Employer) Events",
                            "title_align": "left",
                            "title_size": "16",
                            "type": "timeseries",
                            "yaxis": {
                                "include_zero": true,
                                "label": "",
                                "max": "auto",
                                "min": "auto",
                                "scale": "linear"
                            }
                        },
                        "id": 82014209564702,
                        "layout": {
                            "height": 2,
                            "width": 4,
                            "x": 0,
                            "y": 10
                        }
                    },
                    {
                        "definition": {
                            "autoscale": true,
                            "precision": 0,
                            "requests": [
                                {
                                    "formulas": [
                                        {
                                            "formula": "query1"
                                        }
                                    ],
                                    "queries": [
                                        {
                                            "aggregator": "sum",
                                            "data_source": "metrics",
                                            "name": "query1",
                                            "query": "sum:handshake.iterable_queue.synced_employer_events{env:production}.as_count()"
                                        }
                                    ],
                                    "response_format": "scalar"
                                }
                            ],
                            "title": "Iterable Api Sync (Employer) Events - Sum",
                            "title_align": "left",
                            "title_size": "16",
                            "type": "query_value"
                        },
                        "id": 600843931209500,
                        "layout": {
                            "height": 2,
                            "width": 4,
                            "x": 4,
                            "y": 10
                        }
                    },
                    {
                        "definition": {
                            "legend_columns": [
                                "avg",
                                "min",
                                "max",
                                "value",
                                "sum"
                            ],
                            "legend_layout": "vertical",
                            "markers": [],
                            "requests": [
                                {
                                    "display_type": "bars",
                                    "formulas": [
                                        {
                                            "formula": "query1"
                                        }
                                    ],
                                    "queries": [
                                        {
                                            "data_source": "metrics",
                                            "name": "query1",
                                            "query": "avg:handshake.iterable.employer_event_count{env:production}.as_count()"
                                        }
                                    ],
                                    "response_format": "timeseries",
                                    "style": {
                                        "line_type": "solid",
                                        "line_width": "normal",
                                        "palette": "dog_classic"
                                    }
                                }
                            ],
                            "show_legend": false,
                            "title": "Iterable Api Attempted Sync (Employer) Events",
                            "title_align": "left",
                            "title_size": "16",
                            "type": "timeseries",
                            "yaxis": {
                                "include_zero": true,
                                "label": "",
                                "max": "auto",
                                "min": "auto",
                                "scale": "linear"
                            }
                        },
                        "id": 5655606174072228,
                        "layout": {
                            "height": 2,
                            "width": 4,
                            "x": 8,
                            "y": 10
                        }
                    },
                    {
                        "definition": {
                            "legend_columns": [
                                "avg",
                                "min",
                                "max",
                                "value",
                                "sum"
                            ],
                            "legend_layout": "vertical",
                            "markers": [],
                            "requests": [
                                {
                                    "display_type": "bars",
                                    "q": "sum:handshake.iterable_queue.old_student_user_data_structure.count{env:production}.as_count()",
                                    "style": {
                                        "line_type": "solid",
                                        "line_width": "normal",
                                        "palette": "dog_classic"
                                    }
                                }
                            ],
                            "show_legend": false,
                            "title": "Iterable Queue Sync Old Student User Data",
                            "title_align": "left",
                            "title_size": "16",
                            "type": "timeseries",
                            "yaxis": {
                                "include_zero": true,
                                "label": "",
                                "max": "auto",
                                "min": "auto",
                                "scale": "linear"
                            }
                        },
                        "id": 27639703675006,
                        "layout": {
                            "height": 2,
                            "width": 4,
                            "x": 0,
                            "y": 12
                        }
                    },
                    {
                        "definition": {
                            "legend_columns": [
                                "avg",
                                "min",
                                "max",
                                "value",
                                "sum"
                            ],
                            "legend_layout": "vertical",
                            "markers": [
                                {
                                    "display_type": "error bold",
                                    "label": "\u00a0HIGH LATENCY\u00a0",
                                    "value": "y = 300"
                                }
                            ],
                            "requests": [
                                {
                                    "display_type": "line",
                                    "queries": [
                                        {
                                            "data_source": "metrics",
                                            "name": "query1",
                                            "query": "max:sidekiq.queue.latency{queue:default,env:production} by {env,region}"
                                        }
                                    ],
                                    "response_format": "timeseries",
                                    "style": {
                                        "line_type": "solid",
                                        "line_width": "normal",
                                        "palette": "dog_classic"
                                    }
                                }
                            ],
                            "show_legend": false,
                            "title": "sidekiq.queue.latency with env:production:default",
                            "title_align": "left",
                            "title_size": "16",
                            "type": "timeseries",
                            "yaxis": {
                                "include_zero": true,
                                "label": "",
                                "max": "auto",
                                "min": "auto",
                                "scale": "linear"
                            }
                        },
                        "id": 6959943247238712,
                        "layout": {
                            "height": 2,
                            "width": 4,
                            "x": 4,
                            "y": 12
                        }
                    },
                    {
                        "definition": {
                            "legend_columns": [
                                "avg",
                                "min",
                                "max",
                                "value",
                                "sum"
                            ],
                            "legend_layout": "vertical",
                            "markers": [],
                            "requests": [
                                {
                                    "display_type": "line",
                                    "formulas": [
                                        {
                                            "formula": "query1"
                                        }
                                    ],
                                    "queries": [
                                        {
                                            "data_source": "metrics",
                                            "name": "query1",
                                            "query": "max:sidekiq.queue.size{queue:default,env:production} by {env,region}"
                                        }
                                    ],
                                    "response_format": "timeseries",
                                    "style": {
                                        "line_type": "solid",
                                        "line_width": "normal",
                                        "palette": "dog_classic"
                                    }
                                }
                            ],
                            "show_legend": false,
                            "title": "sidekiq.queue.size with env:production:default",
                            "title_align": "left",
                            "title_size": "16",
                            "type": "timeseries",
                            "yaxis": {
                                "include_zero": true,
                                "label": "",
                                "max": "auto",
                                "min": "auto",
                                "scale": "linear"
                            }
                        },
                        "id": 7134229581748404,
                        "layout": {
                            "height": 2,
                            "width": 4,
                            "x": 8,
                            "y": 12
                        }
                    },
                    {
                        "definition": {
                            "legend_columns": [
                                "avg",
                                "min",
                                "max",
                                "value",
                                "sum"
                            ],
                            "legend_layout": "vertical",
                            "markers": [
                                {
                                    "display_type": "error dashed",
                                    "label": "\u00a0HPA autoscale\u00a0",
                                    "value": "y = 25"
                                }
                            ],
                            "requests": [
                                {
                                    "display_type": "line",
                                    "formulas": [
                                        {
                                            "formula": "query1"
                                        }
                                    ],
                                    "queries": [
                                        {
                                            "data_source": "metrics",
                                            "name": "query1",
                                            "query": "avg:docker.cpu.usage{kube_deployment:handshake-sidekiq-default,cluster-name:production}"
                                        }
                                    ],
                                    "response_format": "timeseries",
                                    "style": {
                                        "line_type": "solid",
                                        "line_width": "normal",
                                        "palette": "dog_classic"
                                    }
                                }
                            ],
                            "show_legend": false,
                            "title": "sidekiq.queue.latency with env:production:default",
                            "title_align": "left",
                            "title_size": "16",
                            "type": "timeseries",
                            "yaxis": {
                                "include_zero": true,
                                "label": "",
                                "max": "auto",
                                "min": "auto",
                                "scale": "linear"
                            }
                        },
                        "id": 1669215553146456,
                        "layout": {
                            "height": 2,
                            "width": 4,
                            "x": 0,
                            "y": 14
                        }
                    },
                    {
                        "definition": {
                            "legend_columns": [
                                "avg",
                                "min",
                                "max",
                                "value",
                                "sum"
                            ],
                            "legend_layout": "vertical",
                            "markers": [
                                {
                                    "display_type": "error dashed",
                                    "label": "\u00a0Max\u00a0",
                                    "value": "y = 25"
                                },
                                {
                                    "display_type": "error dashed",
                                    "label": "\u00a0Min\u00a0",
                                    "value": "y = 3"
                                }
                            ],
                            "requests": [
                                {
                                    "display_type": "line",
                                    "formulas": [
                                        {
                                            "formula": "query2"
                                        }
                                    ],
                                    "queries": [
                                        {
                                            "data_source": "metrics",
                                            "name": "query2",
                                            "query": "avg:kubernetes_state.hpa.desired_replicas{hpa:handshake-sidekiq-default-autoscaler,cluster-name:production}"
                                        }
                                    ],
                                    "response_format": "timeseries",
                                    "style": {
                                        "line_type": "solid",
                                        "line_width": "normal",
                                        "palette": "dog_classic"
                                    }
                                }
                            ],
                            "show_legend": false,
                            "title": "Sidekiq Default Replicas",
                            "title_align": "left",
                            "title_size": "16",
                            "type": "timeseries",
                            "yaxis": {
                                "include_zero": true,
                                "label": "",
                                "max": "auto",
                                "min": "auto",
                                "scale": "linear"
                            }
                        },
                        "id": 8860629328209708,
                        "layout": {
                            "height": 2,
                            "width": 4,
                            "x": 4,
                            "y": 14
                        }
                    },
                    {
                        "definition": {
                            "legend_columns": [
                                "avg",
                                "min",
                                "max",
                                "value",
                                "sum"
                            ],
                            "legend_layout": "vertical",
                            "markers": [],
                            "requests": [
                                {
                                    "display_type": "line",
                                    "formulas": [
                                        {
                                            "formula": "query1"
                                        }
                                    ],
                                    "queries": [
                                        {
                                            "data_source": "metrics",
                                            "name": "query1",
                                            "query": "max:sidekiq.queue.size{queue:high_volume,env:production} by {env,region}"
                                        }
                                    ],
                                    "response_format": "timeseries",
                                    "style": {
                                        "line_type": "solid",
                                        "line_width": "normal",
                                        "palette": "dog_classic"
                                    }
                                }
                            ],
                            "show_legend": false,
                            "title": " Sidekiq high_volume queue size",
                            "title_align": "left",
                            "title_size": "16",
                            "type": "timeseries",
                            "yaxis": {
                                "include_zero": true,
                                "label": "",
                                "max": "auto",
                                "min": "auto",
                                "scale": "linear"
                            }
                        },
                        "id": 1273860391703804,
                        "layout": {
                            "height": 2,
                            "width": 4,
                            "x": 8,
                            "y": 14
                        }
                    }
                ]
            },
            "id": 2543179138329688,
            "layout": {
                "height": 17,
                "width": 12,
                "x": 0,
                "y": 0
            }
        }
    ]
}