{
    "deleted": null,
    "id": 70038342,
    "matching_downtimes": [],
    "message": "{{#is_alert}}\nLooks like a Greenhouse user expired a Job.\nAt the moment, the Job Posting in Handshake will not be automatically expired. Contact the Employers CSM for next steps.\nNote: If a job has an interview schedule, Handshake prevents that posting from expiring. If that is the case, no action is required and this alert can be ignored.\n{{event.text}} \n\n{{/is_alert}}  @slack-emp-ats-alerts,@slack-incidents-te-analytics-int",
    "multi": false,
    "name": "A Greenhouse Job Has Expired",
    "options": {
        "enable_logs_sample": false,
        "groupby_simple_monitor": true,
        "include_tags": true,
        "locked": false,
        "new_host_delay": 300,
        "notify_audit": false,
        "notify_no_data": false,
        "renotify_interval": 0,
        "silenced": {},
        "thresholds": {
            "critical": 1.0
        },
        "timeout_h": 0
    },
    "query": "events(\"\\\"job post expired\\\"\").rollup(\"count\").last(\"5m\") > 1",
    "tags": [
        "team:employer",
        "feature:ats"
    ],
    "type": "event-v2 alert"
}